{
  "resource": "Azure::IoTFirmwareDefense::Firmwares",
  "version": "2024-01-10",
  "operations": [
    {
      "method": "GET",
      "path": "/subscriptions/{subscriptionId}/resourceGroups/{resourceGroupName}/providers/Microsoft.IoTFirmwareDefense/workspaces/{workspaceName}/firmwares",
      "operationId": "Firmwares_ListByWorkspace",
      "pathParameters": [
        {
          "name": "subscriptionId",
          "required": true,
          "type": "string",
          "in": "path",
          "description": "(from URI template)"
        },
        {
          "name": "resourceGroupName",
          "required": true,
          "type": "string",
          "in": "path",
          "description": "(from URI template)"
        },
        {
          "name": "workspaceName",
          "required": true,
          "type": "string",
          "in": "path",
          "description": "(from URI template)"
        }
      ],
      "queryParameters": []
    },
    {
      "method": "PUT",
      "path": "/subscriptions/{subscriptionId}/resourceGroups/{resourceGroupName}/providers/Microsoft.IoTFirmwareDefense/workspaces/{workspaceName}/firmwares/{firmwareId}",
      "operationId": "Firmwares_Create",
      "bodySchema": "Firmware",
      "requiredProperties": [],
      "optionalProperties": [
        "properties",
        "properties.description",
        "properties.fileName",
        "properties.fileSize",
        "properties.model",
        "properties.provisioningState",
        "properties.status",
        "properties.statusMessages",
        "properties.vendor",
        "properties.version"
      ],
      "pathParameters": [
        {
          "name": "subscriptionId",
          "required": true,
          "type": "string",
          "in": "path",
          "description": "(from URI template)"
        },
        {
          "name": "resourceGroupName",
          "required": true,
          "type": "string",
          "in": "path",
          "description": "(from URI template)"
        },
        {
          "name": "workspaceName",
          "required": true,
          "type": "string",
          "in": "path",
          "description": "(from URI template)"
        },
        {
          "name": "firmwareId",
          "required": true,
          "type": "string",
          "in": "path",
          "description": "(from URI template)"
        }
      ],
      "queryParameters": []
    },
    {
      "method": "PATCH",
      "path": "/subscriptions/{subscriptionId}/resourceGroups/{resourceGroupName}/providers/Microsoft.IoTFirmwareDefense/workspaces/{workspaceName}/firmwares/{firmwareId}",
      "operationId": "Firmwares_Update",
      "bodySchema": "FirmwareUpdateDefinition",
      "requiredProperties": [],
      "optionalProperties": [
        "properties",
        "properties.description",
        "properties.fileName",
        "properties.fileSize",
        "properties.model",
        "properties.provisioningState",
        "properties.status",
        "properties.statusMessages",
        "properties.vendor",
        "properties.version"
      ],
      "pathParameters": [
        {
          "name": "subscriptionId",
          "required": true,
          "type": "string",
          "in": "path",
          "description": "(from URI template)"
        },
        {
          "name": "resourceGroupName",
          "required": true,
          "type": "string",
          "in": "path",
          "description": "(from URI template)"
        },
        {
          "name": "workspaceName",
          "required": true,
          "type": "string",
          "in": "path",
          "description": "(from URI template)"
        },
        {
          "name": "firmwareId",
          "required": true,
          "type": "string",
          "in": "path",
          "description": "(from URI template)"
        }
      ],
      "queryParameters": []
    },
    {
      "method": "DELETE",
      "path": "/subscriptions/{subscriptionId}/resourceGroups/{resourceGroupName}/providers/Microsoft.IoTFirmwareDefense/workspaces/{workspaceName}/firmwares/{firmwareId}",
      "operationId": "Firmwares_Delete",
      "pathParameters": [
        {
          "name": "subscriptionId",
          "required": true,
          "type": "string",
          "in": "path",
          "description": "(from URI template)"
        },
        {
          "name": "resourceGroupName",
          "required": true,
          "type": "string",
          "in": "path",
          "description": "(from URI template)"
        },
        {
          "name": "workspaceName",
          "required": true,
          "type": "string",
          "in": "path",
          "description": "(from URI template)"
        },
        {
          "name": "firmwareId",
          "required": true,
          "type": "string",
          "in": "path",
          "description": "(from URI template)"
        }
      ],
      "queryParameters": []
    },
    {
      "method": "GET",
      "path": "/subscriptions/{subscriptionId}/resourceGroups/{resourceGroupName}/providers/Microsoft.IoTFirmwareDefense/workspaces/{workspaceName}/firmwares/{firmwareId}",
      "operationId": "Firmwares_Get",
      "pathParameters": [
        {
          "name": "subscriptionId",
          "required": true,
          "type": "string",
          "in": "path",
          "description": "(from URI template)"
        },
        {
          "name": "resourceGroupName",
          "required": true,
          "type": "string",
          "in": "path",
          "description": "(from URI template)"
        },
        {
          "name": "workspaceName",
          "required": true,
          "type": "string",
          "in": "path",
          "description": "(from URI template)"
        },
        {
          "name": "firmwareId",
          "required": true,
          "type": "string",
          "in": "path",
          "description": "(from URI template)"
        }
      ],
      "queryParameters": []
    }
  ]
}