{
  "resource": "Azure::ApiManagement::NamedValues",
  "version": "unknown",
  "operations": [
    {
      "method": "GET",
      "path": "/subscriptions/{subscriptionId}/resourceGroups/{resourceGroupName}/providers/Microsoft.ApiManagement/service/{serviceName}/workspaces/{workspaceId}/namedValues",
      "operationId": "WorkspaceNamedValue_ListByService",
      "pathParameters": [
        {
          "name": "subscriptionId",
          "required": true,
          "type": "string",
          "in": "path",
          "description": "(from URI template)"
        },
        {
          "name": "resourceGroupName",
          "required": true,
          "type": "string",
          "in": "path",
          "description": "(from URI template)"
        },
        {
          "name": "serviceName",
          "required": true,
          "type": "string",
          "in": "path",
          "description": "(from URI template)"
        },
        {
          "name": "workspaceId",
          "required": true,
          "type": "string",
          "in": "path",
          "description": "(from URI template)"
        }
      ],
      "queryParameters": [
        {
          "name": "$filter",
          "required": false,
          "type": "string",
          "in": "query",
          "description": "|     Field     |     Usage     |     Supported operators     |     Supported functions     |</br>|-------------|-------------|-------------|-------------|</br>| tags | filter | ge, le, eq, ne, gt, lt | substringof, contains, startswith, endswith, any, all |</br>| displayName | filter | ge, le, eq, ne, gt, lt | substringof, contains, startswith, endswith |</br>"
        },
        {
          "name": "isKeyVaultRefreshFailed",
          "required": false,
          "type": "string",
          "in": "query",
          "description": "Query parameter to fetch named value entities based on refresh status."
        }
      ]
    },
    {
      "method": "HEAD",
      "path": "/subscriptions/{subscriptionId}/resourceGroups/{resourceGroupName}/providers/Microsoft.ApiManagement/service/{serviceName}/workspaces/{workspaceId}/namedValues/{namedValueId}",
      "operationId": "WorkspaceNamedValue_GetEntityTag",
      "pathParameters": [
        {
          "name": "subscriptionId",
          "required": true,
          "type": "string",
          "in": "path",
          "description": "(from URI template)"
        },
        {
          "name": "resourceGroupName",
          "required": true,
          "type": "string",
          "in": "path",
          "description": "(from URI template)"
        },
        {
          "name": "serviceName",
          "required": true,
          "type": "string",
          "in": "path",
          "description": "(from URI template)"
        },
        {
          "name": "workspaceId",
          "required": true,
          "type": "string",
          "in": "path",
          "description": "(from URI template)"
        },
        {
          "name": "namedValueId",
          "required": true,
          "type": "string",
          "in": "path",
          "description": "(from URI template)"
        }
      ],
      "queryParameters": []
    },
    {
      "method": "GET",
      "path": "/subscriptions/{subscriptionId}/resourceGroups/{resourceGroupName}/providers/Microsoft.ApiManagement/service/{serviceName}/workspaces/{workspaceId}/namedValues/{namedValueId}",
      "operationId": "WorkspaceNamedValue_Get",
      "pathParameters": [
        {
          "name": "subscriptionId",
          "required": true,
          "type": "string",
          "in": "path",
          "description": "(from URI template)"
        },
        {
          "name": "resourceGroupName",
          "required": true,
          "type": "string",
          "in": "path",
          "description": "(from URI template)"
        },
        {
          "name": "serviceName",
          "required": true,
          "type": "string",
          "in": "path",
          "description": "(from URI template)"
        },
        {
          "name": "workspaceId",
          "required": true,
          "type": "string",
          "in": "path",
          "description": "(from URI template)"
        },
        {
          "name": "namedValueId",
          "required": true,
          "type": "string",
          "in": "path",
          "description": "(from URI template)"
        }
      ],
      "queryParameters": []
    },
    {
      "method": "PUT",
      "path": "/subscriptions/{subscriptionId}/resourceGroups/{resourceGroupName}/providers/Microsoft.ApiManagement/service/{serviceName}/workspaces/{workspaceId}/namedValues/{namedValueId}",
      "operationId": "WorkspaceNamedValue_CreateOrUpdate",
      "bodySchema": "NamedValueCreateContract",
      "pathParameters": [
        {
          "name": "subscriptionId",
          "required": true,
          "type": "string",
          "in": "path",
          "description": "(from URI template)"
        },
        {
          "name": "resourceGroupName",
          "required": true,
          "type": "string",
          "in": "path",
          "description": "(from URI template)"
        },
        {
          "name": "serviceName",
          "required": true,
          "type": "string",
          "in": "path",
          "description": "(from URI template)"
        },
        {
          "name": "workspaceId",
          "required": true,
          "type": "string",
          "in": "path",
          "description": "(from URI template)"
        },
        {
          "name": "namedValueId",
          "required": true,
          "type": "string",
          "in": "path",
          "description": "(from URI template)"
        }
      ],
      "queryParameters": []
    },
    {
      "method": "PATCH",
      "path": "/subscriptions/{subscriptionId}/resourceGroups/{resourceGroupName}/providers/Microsoft.ApiManagement/service/{serviceName}/workspaces/{workspaceId}/namedValues/{namedValueId}",
      "operationId": "WorkspaceNamedValue_Update",
      "bodySchema": "NamedValueUpdateParameters",
      "pathParameters": [
        {
          "name": "subscriptionId",
          "required": true,
          "type": "string",
          "in": "path",
          "description": "(from URI template)"
        },
        {
          "name": "resourceGroupName",
          "required": true,
          "type": "string",
          "in": "path",
          "description": "(from URI template)"
        },
        {
          "name": "serviceName",
          "required": true,
          "type": "string",
          "in": "path",
          "description": "(from URI template)"
        },
        {
          "name": "workspaceId",
          "required": true,
          "type": "string",
          "in": "path",
          "description": "(from URI template)"
        },
        {
          "name": "namedValueId",
          "required": true,
          "type": "string",
          "in": "path",
          "description": "(from URI template)"
        }
      ],
      "queryParameters": []
    },
    {
      "method": "DELETE",
      "path": "/subscriptions/{subscriptionId}/resourceGroups/{resourceGroupName}/providers/Microsoft.ApiManagement/service/{serviceName}/workspaces/{workspaceId}/namedValues/{namedValueId}",
      "operationId": "WorkspaceNamedValue_Delete",
      "pathParameters": [
        {
          "name": "subscriptionId",
          "required": true,
          "type": "string",
          "in": "path",
          "description": "(from URI template)"
        },
        {
          "name": "resourceGroupName",
          "required": true,
          "type": "string",
          "in": "path",
          "description": "(from URI template)"
        },
        {
          "name": "serviceName",
          "required": true,
          "type": "string",
          "in": "path",
          "description": "(from URI template)"
        },
        {
          "name": "workspaceId",
          "required": true,
          "type": "string",
          "in": "path",
          "description": "(from URI template)"
        },
        {
          "name": "namedValueId",
          "required": true,
          "type": "string",
          "in": "path",
          "description": "(from URI template)"
        }
      ],
      "queryParameters": []
    }
  ]
}