{
  "resource": "Azure::AwsConnector::SnsTopics",
  "version": "2024-12-01",
  "operations": [
    {
      "method": "GET",
      "path": "/subscriptions/{subscriptionId}/providers/Microsoft.AwsConnector/snsTopics",
      "operationId": "SnsTopics_ListBySubscription",
      "pathParameters": [
        {
          "name": "subscriptionId",
          "required": true,
          "type": "string",
          "in": "path",
          "description": "(from URI template)"
        }
      ],
      "queryParameters": []
    },
    {
      "method": "GET",
      "path": "/subscriptions/{subscriptionId}/resourceGroups/{resourceGroupName}/providers/Microsoft.AwsConnector/snsTopics",
      "operationId": "SnsTopics_ListByResourceGroup",
      "pathParameters": [
        {
          "name": "subscriptionId",
          "required": true,
          "type": "string",
          "in": "path",
          "description": "(from URI template)"
        },
        {
          "name": "resourceGroupName",
          "required": true,
          "type": "string",
          "in": "path",
          "description": "(from URI template)"
        }
      ],
      "queryParameters": []
    },
    {
      "method": "GET",
      "path": "/subscriptions/{subscriptionId}/resourceGroups/{resourceGroupName}/providers/Microsoft.AwsConnector/snsTopics/{name}",
      "operationId": "SnsTopics_Get",
      "pathParameters": [
        {
          "name": "name",
          "required": true,
          "type": "string",
          "in": "path",
          "description": "Name of SnsTopic"
        },
        {
          "name": "subscriptionId",
          "required": true,
          "type": "string",
          "in": "path",
          "description": "(from URI template)"
        },
        {
          "name": "resourceGroupName",
          "required": true,
          "type": "string",
          "in": "path",
          "description": "(from URI template)"
        }
      ],
      "queryParameters": []
    },
    {
      "method": "PUT",
      "path": "/subscriptions/{subscriptionId}/resourceGroups/{resourceGroupName}/providers/Microsoft.AwsConnector/snsTopics/{name}",
      "operationId": "SnsTopics_CreateOrReplace",
      "bodySchema": "SnsTopic",
      "requiredProperties": [],
      "optionalProperties": [
        "properties",
        "properties.arn",
        "properties.awsAccountId",
        "properties.awsProperties",
        "properties.awsProperties.archivePolicy",
        "properties.awsProperties.contentBasedDeduplication",
        "properties.awsProperties.dataProtectionPolicy",
        "properties.awsProperties.deliveryStatusLogging",
        "properties.awsProperties.displayName",
        "properties.awsProperties.fifoTopic",
        "properties.awsProperties.kmsMasterKeyId",
        "properties.awsProperties.signatureVersion",
        "properties.awsProperties.subscription",
        "properties.awsProperties.tags",
        "properties.awsProperties.topicArn",
        "properties.awsProperties.topicName",
        "properties.awsProperties.tracingConfig",
        "properties.awsRegion",
        "properties.awsSourceSchema",
        "properties.awsTags",
        "properties.provisioningState",
        "properties.publicCloudConnectorsResourceId",
        "properties.publicCloudResourceName"
      ],
      "pathParameters": [
        {
          "name": "name",
          "required": true,
          "type": "string",
          "in": "path",
          "description": "Name of SnsTopic"
        },
        {
          "name": "subscriptionId",
          "required": true,
          "type": "string",
          "in": "path",
          "description": "(from URI template)"
        },
        {
          "name": "resourceGroupName",
          "required": true,
          "type": "string",
          "in": "path",
          "description": "(from URI template)"
        }
      ],
      "queryParameters": []
    },
    {
      "method": "PATCH",
      "path": "/subscriptions/{subscriptionId}/resourceGroups/{resourceGroupName}/providers/Microsoft.AwsConnector/snsTopics/{name}",
      "operationId": "SnsTopics_Update",
      "bodySchema": "SnsTopicTagsUpdate",
      "requiredProperties": [],
      "optionalProperties": [
        "tags"
      ],
      "pathParameters": [
        {
          "name": "name",
          "required": true,
          "type": "string",
          "in": "path",
          "description": "Name of SnsTopic"
        },
        {
          "name": "subscriptionId",
          "required": true,
          "type": "string",
          "in": "path",
          "description": "(from URI template)"
        },
        {
          "name": "resourceGroupName",
          "required": true,
          "type": "string",
          "in": "path",
          "description": "(from URI template)"
        }
      ],
      "queryParameters": []
    },
    {
      "method": "DELETE",
      "path": "/subscriptions/{subscriptionId}/resourceGroups/{resourceGroupName}/providers/Microsoft.AwsConnector/snsTopics/{name}",
      "operationId": "SnsTopics_Delete",
      "pathParameters": [
        {
          "name": "name",
          "required": true,
          "type": "string",
          "in": "path",
          "description": "Name of SnsTopic"
        },
        {
          "name": "subscriptionId",
          "required": true,
          "type": "string",
          "in": "path",
          "description": "(from URI template)"
        },
        {
          "name": "resourceGroupName",
          "required": true,
          "type": "string",
          "in": "path",
          "description": "(from URI template)"
        }
      ],
      "queryParameters": []
    }
  ]
}