{
  "resource": "Azure::AwsConnector::Ec2Ipams",
  "version": "2024-12-01",
  "operations": [
    {
      "method": "GET",
      "path": "/subscriptions/{subscriptionId}/providers/Microsoft.AwsConnector/ec2Ipams",
      "operationId": "Ec2Ipams_ListBySubscription",
      "pathParameters": [
        {
          "name": "subscriptionId",
          "required": true,
          "type": "string",
          "in": "path",
          "description": "(from URI template)"
        }
      ],
      "queryParameters": []
    },
    {
      "method": "GET",
      "path": "/subscriptions/{subscriptionId}/resourceGroups/{resourceGroupName}/providers/Microsoft.AwsConnector/ec2Ipams",
      "operationId": "Ec2Ipams_ListByResourceGroup",
      "pathParameters": [
        {
          "name": "subscriptionId",
          "required": true,
          "type": "string",
          "in": "path",
          "description": "(from URI template)"
        },
        {
          "name": "resourceGroupName",
          "required": true,
          "type": "string",
          "in": "path",
          "description": "(from URI template)"
        }
      ],
      "queryParameters": []
    },
    {
      "method": "GET",
      "path": "/subscriptions/{subscriptionId}/resourceGroups/{resourceGroupName}/providers/Microsoft.AwsConnector/ec2Ipams/{name}",
      "operationId": "Ec2Ipams_Get",
      "pathParameters": [
        {
          "name": "name",
          "required": true,
          "type": "string",
          "in": "path",
          "description": "Name of Ec2Ipam"
        },
        {
          "name": "subscriptionId",
          "required": true,
          "type": "string",
          "in": "path",
          "description": "(from URI template)"
        },
        {
          "name": "resourceGroupName",
          "required": true,
          "type": "string",
          "in": "path",
          "description": "(from URI template)"
        }
      ],
      "queryParameters": []
    },
    {
      "method": "PUT",
      "path": "/subscriptions/{subscriptionId}/resourceGroups/{resourceGroupName}/providers/Microsoft.AwsConnector/ec2Ipams/{name}",
      "operationId": "Ec2Ipams_CreateOrReplace",
      "bodySchema": "Ec2Ipam",
      "requiredProperties": [],
      "optionalProperties": [
        "properties",
        "properties.arn",
        "properties.awsAccountId",
        "properties.awsProperties",
        "properties.awsProperties.defaultResourceDiscoveryAssociationId",
        "properties.awsProperties.defaultResourceDiscoveryId",
        "properties.awsProperties.description",
        "properties.awsProperties.ipamArn",
        "properties.awsProperties.ipamId",
        "properties.awsProperties.ipamRegion",
        "properties.awsProperties.operatingRegions",
        "properties.awsProperties.ownerId",
        "properties.awsProperties.privateDefaultScopeId",
        "properties.awsProperties.publicDefaultScopeId",
        "properties.awsProperties.resourceDiscoveryAssociationCount",
        "properties.awsProperties.scopeCount",
        "properties.awsProperties.state",
        "properties.awsProperties.state.value",
        "properties.awsProperties.stateMessage",
        "properties.awsProperties.tags",
        "properties.awsProperties.tier",
        "properties.awsProperties.tier.value",
        "properties.awsRegion",
        "properties.awsSourceSchema",
        "properties.awsTags",
        "properties.provisioningState",
        "properties.publicCloudConnectorsResourceId",
        "properties.publicCloudResourceName"
      ],
      "pathParameters": [
        {
          "name": "name",
          "required": true,
          "type": "string",
          "in": "path",
          "description": "Name of Ec2Ipam"
        },
        {
          "name": "subscriptionId",
          "required": true,
          "type": "string",
          "in": "path",
          "description": "(from URI template)"
        },
        {
          "name": "resourceGroupName",
          "required": true,
          "type": "string",
          "in": "path",
          "description": "(from URI template)"
        }
      ],
      "queryParameters": []
    },
    {
      "method": "PATCH",
      "path": "/subscriptions/{subscriptionId}/resourceGroups/{resourceGroupName}/providers/Microsoft.AwsConnector/ec2Ipams/{name}",
      "operationId": "Ec2Ipams_Update",
      "bodySchema": "Ec2IpamTagsUpdate",
      "requiredProperties": [],
      "optionalProperties": [
        "tags"
      ],
      "pathParameters": [
        {
          "name": "name",
          "required": true,
          "type": "string",
          "in": "path",
          "description": "Name of Ec2Ipam"
        },
        {
          "name": "subscriptionId",
          "required": true,
          "type": "string",
          "in": "path",
          "description": "(from URI template)"
        },
        {
          "name": "resourceGroupName",
          "required": true,
          "type": "string",
          "in": "path",
          "description": "(from URI template)"
        }
      ],
      "queryParameters": []
    },
    {
      "method": "DELETE",
      "path": "/subscriptions/{subscriptionId}/resourceGroups/{resourceGroupName}/providers/Microsoft.AwsConnector/ec2Ipams/{name}",
      "operationId": "Ec2Ipams_Delete",
      "pathParameters": [
        {
          "name": "name",
          "required": true,
          "type": "string",
          "in": "path",
          "description": "Name of Ec2Ipam"
        },
        {
          "name": "subscriptionId",
          "required": true,
          "type": "string",
          "in": "path",
          "description": "(from URI template)"
        },
        {
          "name": "resourceGroupName",
          "required": true,
          "type": "string",
          "in": "path",
          "description": "(from URI template)"
        }
      ],
      "queryParameters": []
    }
  ]
}