{
  "resource": "Azure::HealthcareApis::PrivateEndpointConnections",
  "version": "2020-03-30",
  "operations": [
    {
      "method": "GET",
      "path": "/subscriptions/{subscriptionId}/resourceGroups/{resourceGroupName}/providers/Microsoft.HealthcareApis/services/{resourceName}/privateEndpointConnections",
      "operationId": "PrivateEndpointConnections_ListByService",
      "pathParameters": [
        {
          "name": "subscriptionId",
          "required": true,
          "type": "string",
          "in": "path",
          "description": "The subscription identifier."
        },
        {
          "name": "resourceGroupName",
          "required": true,
          "type": "string",
          "in": "path",
          "description": "The name of the resource group that contains the service instance."
        },
        {
          "name": "resourceName",
          "required": true,
          "type": "string",
          "in": "path",
          "description": "The name of the service instance."
        }
      ],
      "queryParameters": [
        {
          "name": "api-version",
          "required": true,
          "type": "string",
          "in": "query",
          "description": "Client Api Version."
        }
      ]
    },
    {
      "method": "GET",
      "path": "/subscriptions/{subscriptionId}/resourceGroups/{resourceGroupName}/providers/Microsoft.HealthcareApis/services/{resourceName}/privateEndpointConnections/{privateEndpointConnectionName}",
      "operationId": "PrivateEndpointConnections_Get",
      "pathParameters": [
        {
          "name": "subscriptionId",
          "required": true,
          "type": "string",
          "in": "path",
          "description": "The subscription identifier."
        },
        {
          "name": "resourceGroupName",
          "required": true,
          "type": "string",
          "in": "path",
          "description": "The name of the resource group that contains the service instance."
        },
        {
          "name": "resourceName",
          "required": true,
          "type": "string",
          "in": "path",
          "description": "The name of the service instance."
        },
        {
          "name": "privateEndpointConnectionName",
          "required": true,
          "type": "string",
          "in": "path",
          "description": "(from URI template)"
        }
      ],
      "queryParameters": [
        {
          "name": "api-version",
          "required": true,
          "type": "string",
          "in": "query",
          "description": "Client Api Version."
        }
      ]
    },
    {
      "method": "PUT",
      "path": "/subscriptions/{subscriptionId}/resourceGroups/{resourceGroupName}/providers/Microsoft.HealthcareApis/services/{resourceName}/privateEndpointConnections/{privateEndpointConnectionName}",
      "operationId": "PrivateEndpointConnections_CreateOrUpdate",
      "bodySchema": "PrivateEndpointConnection",
      "pathParameters": [
        {
          "name": "subscriptionId",
          "required": true,
          "type": "string",
          "in": "path",
          "description": "The subscription identifier."
        },
        {
          "name": "resourceGroupName",
          "required": true,
          "type": "string",
          "in": "path",
          "description": "The name of the resource group that contains the service instance."
        },
        {
          "name": "resourceName",
          "required": true,
          "type": "string",
          "in": "path",
          "description": "The name of the service instance."
        },
        {
          "name": "privateEndpointConnectionName",
          "required": true,
          "type": "string",
          "in": "path",
          "description": "(from URI template)"
        }
      ],
      "queryParameters": [
        {
          "name": "api-version",
          "required": true,
          "type": "string",
          "in": "query",
          "description": "Client Api Version."
        }
      ]
    },
    {
      "method": "DELETE",
      "path": "/subscriptions/{subscriptionId}/resourceGroups/{resourceGroupName}/providers/Microsoft.HealthcareApis/services/{resourceName}/privateEndpointConnections/{privateEndpointConnectionName}",
      "operationId": "PrivateEndpointConnections_Delete",
      "pathParameters": [
        {
          "name": "subscriptionId",
          "required": true,
          "type": "string",
          "in": "path",
          "description": "The subscription identifier."
        },
        {
          "name": "resourceGroupName",
          "required": true,
          "type": "string",
          "in": "path",
          "description": "The name of the resource group that contains the service instance."
        },
        {
          "name": "resourceName",
          "required": true,
          "type": "string",
          "in": "path",
          "description": "The name of the service instance."
        },
        {
          "name": "privateEndpointConnectionName",
          "required": true,
          "type": "string",
          "in": "path",
          "description": "(from URI template)"
        }
      ],
      "queryParameters": [
        {
          "name": "api-version",
          "required": true,
          "type": "string",
          "in": "query",
          "description": "Client Api Version."
        }
      ]
    }
  ]
}