{
  "resource": "Azure::MobileNetwork::AttachedDataNetworks",
  "version": "2023-09-01",
  "operations": [
    {
      "method": "DELETE",
      "path": "/subscriptions/{subscriptionId}/resourceGroups/{resourceGroupName}/providers/Microsoft.MobileNetwork/packetCoreControlPlanes/{packetCoreControlPlaneName}/packetCoreDataPlanes/{packetCoreDataPlaneName}/attachedDataNetworks/{attachedDataNetworkName}",
      "operationId": "AttachedDataNetworks_Delete",
      "pathParameters": [
        {
          "name": "subscriptionId",
          "required": true,
          "type": "string",
          "in": "path",
          "description": "(from URI template)"
        },
        {
          "name": "resourceGroupName",
          "required": true,
          "type": "string",
          "in": "path",
          "description": "(from URI template)"
        },
        {
          "name": "packetCoreControlPlaneName",
          "required": true,
          "type": "string",
          "in": "path",
          "description": "(from URI template)"
        },
        {
          "name": "packetCoreDataPlaneName",
          "required": true,
          "type": "string",
          "in": "path",
          "description": "(from URI template)"
        },
        {
          "name": "attachedDataNetworkName",
          "required": true,
          "type": "string",
          "in": "path",
          "description": "(from URI template)"
        }
      ],
      "queryParameters": []
    },
    {
      "method": "GET",
      "path": "/subscriptions/{subscriptionId}/resourceGroups/{resourceGroupName}/providers/Microsoft.MobileNetwork/packetCoreControlPlanes/{packetCoreControlPlaneName}/packetCoreDataPlanes/{packetCoreDataPlaneName}/attachedDataNetworks/{attachedDataNetworkName}",
      "operationId": "AttachedDataNetworks_Get",
      "pathParameters": [
        {
          "name": "subscriptionId",
          "required": true,
          "type": "string",
          "in": "path",
          "description": "(from URI template)"
        },
        {
          "name": "resourceGroupName",
          "required": true,
          "type": "string",
          "in": "path",
          "description": "(from URI template)"
        },
        {
          "name": "packetCoreControlPlaneName",
          "required": true,
          "type": "string",
          "in": "path",
          "description": "(from URI template)"
        },
        {
          "name": "packetCoreDataPlaneName",
          "required": true,
          "type": "string",
          "in": "path",
          "description": "(from URI template)"
        },
        {
          "name": "attachedDataNetworkName",
          "required": true,
          "type": "string",
          "in": "path",
          "description": "(from URI template)"
        }
      ],
      "queryParameters": []
    },
    {
      "method": "PUT",
      "path": "/subscriptions/{subscriptionId}/resourceGroups/{resourceGroupName}/providers/Microsoft.MobileNetwork/packetCoreControlPlanes/{packetCoreControlPlaneName}/packetCoreDataPlanes/{packetCoreDataPlaneName}/attachedDataNetworks/{attachedDataNetworkName}",
      "operationId": "AttachedDataNetworks_CreateOrUpdate",
      "bodySchema": "AttachedDataNetwork",
      "requiredProperties": [
        "properties",
        "properties.dnsAddresses",
        "properties.userPlaneDataInterface"
      ],
      "optionalProperties": [
        "properties.naptConfiguration",
        "properties.naptConfiguration.enabled",
        "properties.naptConfiguration.pinholeLimits",
        "properties.naptConfiguration.pinholeTimeouts",
        "properties.naptConfiguration.pinholeTimeouts.icmp",
        "properties.naptConfiguration.pinholeTimeouts.tcp",
        "properties.naptConfiguration.pinholeTimeouts.udp",
        "properties.naptConfiguration.portRange",
        "properties.naptConfiguration.portRange.maxPort",
        "properties.naptConfiguration.portRange.minPort",
        "properties.naptConfiguration.portReuseHoldTime",
        "properties.naptConfiguration.portReuseHoldTime.tcp",
        "properties.naptConfiguration.portReuseHoldTime.udp",
        "properties.provisioningState",
        "properties.userEquipmentAddressPoolPrefix",
        "properties.userEquipmentStaticAddressPoolPrefix"
      ],
      "pathParameters": [
        {
          "name": "subscriptionId",
          "required": true,
          "type": "string",
          "in": "path",
          "description": "(from URI template)"
        },
        {
          "name": "resourceGroupName",
          "required": true,
          "type": "string",
          "in": "path",
          "description": "(from URI template)"
        },
        {
          "name": "packetCoreControlPlaneName",
          "required": true,
          "type": "string",
          "in": "path",
          "description": "(from URI template)"
        },
        {
          "name": "packetCoreDataPlaneName",
          "required": true,
          "type": "string",
          "in": "path",
          "description": "(from URI template)"
        },
        {
          "name": "attachedDataNetworkName",
          "required": true,
          "type": "string",
          "in": "path",
          "description": "(from URI template)"
        }
      ],
      "queryParameters": []
    },
    {
      "method": "PATCH",
      "path": "/subscriptions/{subscriptionId}/resourceGroups/{resourceGroupName}/providers/Microsoft.MobileNetwork/packetCoreControlPlanes/{packetCoreControlPlaneName}/packetCoreDataPlanes/{packetCoreDataPlaneName}/attachedDataNetworks/{attachedDataNetworkName}",
      "operationId": "AttachedDataNetworks_UpdateTags",
      "bodySchema": "TagsObject",
      "pathParameters": [
        {
          "name": "subscriptionId",
          "required": true,
          "type": "string",
          "in": "path",
          "description": "(from URI template)"
        },
        {
          "name": "resourceGroupName",
          "required": true,
          "type": "string",
          "in": "path",
          "description": "(from URI template)"
        },
        {
          "name": "packetCoreControlPlaneName",
          "required": true,
          "type": "string",
          "in": "path",
          "description": "(from URI template)"
        },
        {
          "name": "packetCoreDataPlaneName",
          "required": true,
          "type": "string",
          "in": "path",
          "description": "(from URI template)"
        },
        {
          "name": "attachedDataNetworkName",
          "required": true,
          "type": "string",
          "in": "path",
          "description": "(from URI template)"
        }
      ],
      "queryParameters": []
    },
    {
      "method": "GET",
      "path": "/subscriptions/{subscriptionId}/resourceGroups/{resourceGroupName}/providers/Microsoft.MobileNetwork/packetCoreControlPlanes/{packetCoreControlPlaneName}/packetCoreDataPlanes/{packetCoreDataPlaneName}/attachedDataNetworks",
      "operationId": "AttachedDataNetworks_ListByPacketCoreDataPlane",
      "pathParameters": [
        {
          "name": "subscriptionId",
          "required": true,
          "type": "string",
          "in": "path",
          "description": "(from URI template)"
        },
        {
          "name": "resourceGroupName",
          "required": true,
          "type": "string",
          "in": "path",
          "description": "(from URI template)"
        },
        {
          "name": "packetCoreControlPlaneName",
          "required": true,
          "type": "string",
          "in": "path",
          "description": "(from URI template)"
        },
        {
          "name": "packetCoreDataPlaneName",
          "required": true,
          "type": "string",
          "in": "path",
          "description": "(from URI template)"
        }
      ],
      "queryParameters": []
    }
  ]
}