{
  "resource": "Azure::Network::CustomIpPrefixes",
  "version": "2020-07-01",
  "operations": [
    {
      "method": "DELETE",
      "path": "/subscriptions/{subscriptionId}/resourceGroups/{resourceGroupName}/providers/Microsoft.Network/customIpPrefixes/{customIpPrefixName}",
      "operationId": "CustomIPPrefixes_Delete",
      "pathParameters": [
        {
          "name": "resourceGroupName",
          "required": true,
          "type": "string",
          "in": "path",
          "description": "The name of the resource group."
        },
        {
          "name": "customIpPrefixName",
          "required": true,
          "type": "string",
          "in": "path",
          "description": "The name of the CustomIpPrefix."
        },
        {
          "name": "subscriptionId",
          "required": true,
          "type": "string",
          "in": "path",
          "description": "(from URI template)"
        }
      ],
      "queryParameters": []
    },
    {
      "method": "GET",
      "path": "/subscriptions/{subscriptionId}/resourceGroups/{resourceGroupName}/providers/Microsoft.Network/customIpPrefixes/{customIpPrefixName}",
      "operationId": "CustomIPPrefixes_Get",
      "pathParameters": [
        {
          "name": "resourceGroupName",
          "required": true,
          "type": "string",
          "in": "path",
          "description": "The name of the resource group."
        },
        {
          "name": "customIpPrefixName",
          "required": true,
          "type": "string",
          "in": "path",
          "description": "The name of the custom IP prefix."
        },
        {
          "name": "subscriptionId",
          "required": true,
          "type": "string",
          "in": "path",
          "description": "(from URI template)"
        }
      ],
      "queryParameters": [
        {
          "name": "$expand",
          "required": false,
          "type": "string",
          "in": "query",
          "description": "Expands referenced resources."
        }
      ]
    },
    {
      "method": "PUT",
      "path": "/subscriptions/{subscriptionId}/resourceGroups/{resourceGroupName}/providers/Microsoft.Network/customIpPrefixes/{customIpPrefixName}",
      "operationId": "CustomIPPrefixes_CreateOrUpdate",
      "bodySchema": "CustomIpPrefix",
      "requiredProperties": [],
      "optionalProperties": [
        "etag",
        "properties",
        "properties.cidr",
        "properties.commissionedState",
        "properties.provisioningState",
        "properties.publicIpPrefixes",
        "properties.resourceGuid",
        "zones"
      ],
      "pathParameters": [
        {
          "name": "resourceGroupName",
          "required": true,
          "type": "string",
          "in": "path",
          "description": "The name of the resource group."
        },
        {
          "name": "customIpPrefixName",
          "required": true,
          "type": "string",
          "in": "path",
          "description": "The name of the custom IP prefix."
        },
        {
          "name": "subscriptionId",
          "required": true,
          "type": "string",
          "in": "path",
          "description": "(from URI template)"
        }
      ],
      "queryParameters": []
    },
    {
      "method": "PATCH",
      "path": "/subscriptions/{subscriptionId}/resourceGroups/{resourceGroupName}/providers/Microsoft.Network/customIpPrefixes/{customIpPrefixName}",
      "operationId": "CustomIPPrefixes_UpdateTags",
      "bodySchema": "TagsObject",
      "pathParameters": [
        {
          "name": "resourceGroupName",
          "required": true,
          "type": "string",
          "in": "path",
          "description": "The name of the resource group."
        },
        {
          "name": "customIpPrefixName",
          "required": true,
          "type": "string",
          "in": "path",
          "description": "The name of the custom IP prefix."
        },
        {
          "name": "subscriptionId",
          "required": true,
          "type": "string",
          "in": "path",
          "description": "(from URI template)"
        }
      ],
      "queryParameters": []
    },
    {
      "method": "GET",
      "path": "/subscriptions/{subscriptionId}/providers/Microsoft.Network/customIpPrefixes",
      "operationId": "CustomIPPrefixes_ListAll",
      "pathParameters": [
        {
          "name": "subscriptionId",
          "required": true,
          "type": "string",
          "in": "path",
          "description": "(from URI template)"
        }
      ],
      "queryParameters": []
    },
    {
      "method": "GET",
      "path": "/subscriptions/{subscriptionId}/resourceGroups/{resourceGroupName}/providers/Microsoft.Network/customIpPrefixes",
      "operationId": "CustomIPPrefixes_List",
      "pathParameters": [
        {
          "name": "resourceGroupName",
          "required": true,
          "type": "string",
          "in": "path",
          "description": "The name of the resource group."
        },
        {
          "name": "subscriptionId",
          "required": true,
          "type": "string",
          "in": "path",
          "description": "(from URI template)"
        }
      ],
      "queryParameters": []
    }
  ]
}